x_net_django_color_field/__init__.py
x_net_django_color_field/forms.py
x_net_django_color_field/models.py
x_net_django_color_field/validators.py
x_net_django_color_field-1.0.1.dist-info/LICENSE
x_net_django_color_field-1.0.1.dist-info/METADATA
x_net_django_color_field-1.0.1.dist-info/WHEEL
x_net_django_color_field-1.0.1.dist-info/top_level.txt
x_net_django_color_field-1.0.1.dist-info/RECORD
