Metadata-Version: 2.1
Name: x-net-django-color-field
Version: 1.0.1
Summary: Django Color Field
Home-page: https://github.com/x-net-services/x-net-django-color-field
Author: X-Net Services GmbH
Author-email: support-software@x-net.at
License: MIT
Platform: UNKNOWN
Classifier: Framework :: Django
Classifier: Framework :: Django :: 2.2
Classifier: License :: OSI Approved :: MIT License
Classifier: Programming Language :: Python :: 3.6
Classifier: Topic :: Internet :: WWW/HTTP
Requires-Python: >=3.6
Requires-Dist: Django (>=2.2.17)
